{
  "generatedAt": "2026-05-03T15:31:40.426Z",
  "systemName": "Procyon A",
  "planetName": "Procyon V",
  "planetWikiPath": "/wiki/Procyon_V",
  "moons": [
    {
      "type": "moon",
      "name": "Procyon V-a",
      "orbitIndex": 1,
      "wikiPath": "/wiki/Procyon_V-a",
      "sourceUrl": "https://starfield.fandom.com/wiki/Procyon_V-a",
      "sourcePage": "Procyon V-a",
      "generalInfo": [
        {
          "key": "system",
          "label": "System",
          "value": "Procyon A"
        },
        {
          "key": "orbits",
          "label": "Orbiting",
          "value": "Procyon V"
        },
        {
          "key": "type",
          "label": "Type",
          "value": "Ice"
        },
        {
          "key": "gravity",
          "label": "Gravity",
          "value": "0.14 G"
        },
        {
          "key": "temp",
          "label": "Temperature",
          "value": "Frozen"
        },
        {
          "key": "atmosphere",
          "label": "Atmosphere",
          "value": "None"
        },
        {
          "key": "magneto",
          "label": "Magnetosphere",
          "value": "None"
        },
        {
          "key": "fauna",
          "label": "Fauna",
          "value": "None"
        },
        {
          "key": "flora",
          "label": "Flora",
          "value": "None"
        },
        {
          "key": "water",
          "label": "Water",
          "value": "Chemical"
        },
        {
          "key": "traits",
          "label": "Traits",
          "value": "Crystalline Crust"
        }
      ],
      "infoStatus": "ok"
    },
    {
      "type": "moon",
      "name": "Procyon V-b",
      "orbitIndex": 2,
      "wikiPath": "/wiki/Procyon_V-b",
      "sourceUrl": "https://starfield.fandom.com/wiki/Procyon_V-b",
      "sourcePage": "Procyon V-b",
      "generalInfo": [
        {
          "key": "system",
          "label": "System",
          "value": "Procyon A"
        },
        {
          "key": "orbits",
          "label": "Orbiting",
          "value": "Procyon V"
        },
        {
          "key": "type",
          "label": "Type",
          "value": "Ice"
        },
        {
          "key": "gravity",
          "label": "Gravity",
          "value": "0.31 G"
        },
        {
          "key": "temp",
          "label": "Temperature",
          "value": "Frozen"
        },
        {
          "key": "atmosphere",
          "label": "Atmosphere",
          "value": "None"
        },
        {
          "key": "magneto",
          "label": "Magnetosphere",
          "value": "None"
        },
        {
          "key": "fauna",
          "label": "Fauna",
          "value": "None"
        },
        {
          "key": "flora",
          "label": "Flora",
          "value": "None"
        },
        {
          "key": "water",
          "label": "Water",
          "value": "Chemical"
        },
        {
          "key": "traits",
          "label": "Traits",
          "value": "Crystalline Crust"
        }
      ],
      "infoStatus": "ok"
    },
    {
      "type": "moon",
      "name": "Procyon V-c",
      "orbitIndex": 3,
      "wikiPath": "/wiki/Procyon_V-c",
      "sourceUrl": "https://starfield.fandom.com/wiki/Procyon_V-c",
      "sourcePage": "Procyon V-c",
      "generalInfo": [
        {
          "key": "system",
          "label": "System",
          "value": "Procyon A"
        },
        {
          "key": "orbits",
          "label": "Orbiting",
          "value": "Procyon V"
        },
        {
          "key": "type",
          "label": "Type",
          "value": "Ice"
        },
        {
          "key": "gravity",
          "label": "Gravity",
          "value": "0.27 G"
        },
        {
          "key": "temp",
          "label": "Temperature",
          "value": "Frozen"
        },
        {
          "key": "atmosphere",
          "label": "Atmosphere",
          "value": "None"
        },
        {
          "key": "magneto",
          "label": "Magnetosphere",
          "value": "None"
        },
        {
          "key": "fauna",
          "label": "Fauna",
          "value": "None"
        },
        {
          "key": "flora",
          "label": "Flora",
          "value": "None"
        },
        {
          "key": "water",
          "label": "Water",
          "value": "Heavy Metal"
        },
        {
          "key": "traits",
          "label": "Traits",
          "value": "None"
        }
      ],
      "infoStatus": "ok"
    }
  ]
}
